{
  "version": "0.2",
  "ships": [
    {
      "id": 1,
      "name": "泛用型布里",
      "faction": "其他",
      "ship_class": "驱逐",
      "rarity": "精锐",
      "owned": false,
      "breakthrough": 0,
      "can_remodel": false,
      "remodel_date": "",
      "remodeled": false,
      "oath": false,
      "level_120": false,
      "acquire_main": "兑换、赠送",
      "acquire_detail": "日/周常任务、月度签到、活动任务、商店兑换、主线普通关卡三星奖励、新兵训练、礼包购买",
      "build_time": "",
      "drop_locations": [],
      "shop_exchange": "勋章、演习",
      "is_permanent": true,
      "debut_event": "",
      "release_date": "2017-05-25",
      "notes": "无法建造",
      "tech_points_obtain": 0,
      "tech_points_max": 0,
      "tech_points_120": 0,
      "bonus_obtain": [],
      "bonus_120": [],
      "tech_affects": [
        "驱逐"
      ],
      "tech_durability_obtain": 0,
      "tech_durability_max": 0,
      "tech_durability_120": 0,
      "tech_firepower_obtain": 0,
      "tech_firepower_max": 0,
      "tech_firepower_120": 0,
      "tech_torpedo_obtain": 0,
      "tech_torpedo_max": 0,
      "tech_torpedo_120": 0,
      "tech_aa_obtain": 0,
      "tech_aa_max": 0,
      "tech_aa_120": 0,
      "tech_aviation_obtain": 0,
      "tech_aviation_max": 0,
      "tech_aviation_120": 0,
      "tech_accuracy_obtain": 0,
      "tech_accuracy_max": 0,
      "tech_accuracy_120": 0,
      "tech_reload_obtain": 0,
      "tech_reload_max": 0,
      "tech_reload_120": 0,
      "tech_mobility_obtain": 0,
      "tech_mobility_max": 0,
      "tech_mobility_120": 0,
      "tech_antisub_obtain": 0,
      "tech_antisub_max": 0,
      "tech_antisub_120": 0,
      "image_path": "images/bulin.png"
    },
    {
      "id": 2,
      "name": "试作型布里MKII",
      "faction": "其他",
      "ship_class": "驱逐",
      "rarity": "超稀有",
      "owned": false,
      "breakthrough": 0,
      "can_remodel": false,
      "remodel_date": "",
      "remodeled": false,
      "oath": false,
      "level_120": false,
      "acquire_main": "兑换、赠送",
      "acquire_detail": "日/周常任务、月度签到、活动任务、商店兑换、主线普通关卡三星奖励、新兵训练、礼包购买",
      "build_time": "",
      "drop_locations": [],
      "shop_exchange": "勋章、演习",
      "is_permanent": true,
      "debut_event": "",
      "release_date": "2017-05-25",
      "notes": "无法建造",
      "tech_points_obtain": 0,
      "tech_points_max": 0,
      "tech_points_120": 0,
      "bonus_obtain": [],
      "bonus_120": [],
      "tech_affects": [
        "驱逐"
      ],
      "tech_durability_obtain": 0,
      "tech_durability_max": 0,
      "tech_durability_120": 0,
      "tech_firepower_obtain": 0,
      "tech_firepower_max": 0,
      "tech_firepower_120": 0,
      "tech_torpedo_obtain": 0,
      "tech_torpedo_max": 0,
      "tech_torpedo_120": 0,
      "tech_aa_obtain": 0,
      "tech_aa_max": 0,
      "tech_aa_120": 0,
      "tech_aviation_obtain": 0,
      "tech_aviation_max": 0,
      "tech_aviation_120": 0,
      "tech_accuracy_obtain": 0,
      "tech_accuracy_max": 0,
      "tech_accuracy_120": 0,
      "tech_reload_obtain": 0,
      "tech_reload_max": 0,
      "tech_reload_120": 0,
      "tech_mobility_obtain": 0,
      "tech_mobility_max": 0,
      "tech_mobility_120": 0,
      "tech_antisub_obtain": 0,
      "tech_antisub_max": 0,
      "tech_antisub_120": 0,
      "image_path": "images/trial_bulin_mkii.png"
    },
    {
      "id": 3,
      "name": "特装型布里MKIII",
      "faction": "其他",
      "ship_class": "驱逐",
      "rarity": "海上传奇",
      "owned": false,
      "breakthrough": 0,
      "can_remodel": false,
      "remodel_date": "",
      "remodeled": false,
      "oath": false,
      "level_120": false,
      "acquire_main": "兑换、赠送",
      "acquire_detail": "世界巡游赠送、带有UR的大型EX活动累计PT获取、布里支援计划、商店兑换",
      "build_time": "",
      "drop_locations": [],
      "shop_exchange": "原型商店",
      "is_permanent": true,
      "debut_event": "蝶海梦花",
      "release_date": "2020-09-17",
      "notes": "无法建造",
      "tech_points_obtain": 0,
      "tech_points_max": 0,
      "tech_points_120": 0,
      "bonus_obtain": [],
      "bonus_120": [],
      "tech_affects": [
        "驱逐"
      ],
      "tech_durability_obtain": 0,
      "tech_durability_max": 0,
      "tech_durability_120": 0,
      "tech_firepower_obtain": 0,
      "tech_firepower_max": 0,
      "tech_firepower_120": 0,
      "tech_torpedo_obtain": 0,
      "tech_torpedo_max": 0,
      "tech_torpedo_120": 0,
      "tech_aa_obtain": 0,
      "tech_aa_max": 0,
      "tech_aa_120": 0,
      "tech_aviation_obtain": 0,
      "tech_aviation_max": 0,
      "tech_aviation_120": 0,
      "tech_accuracy_obtain": 0,
      "tech_accuracy_max": 0,
      "tech_accuracy_120": 0,
      "tech_reload_obtain": 0,
      "tech_reload_max": 0,
      "tech_reload_120": 0,
      "tech_mobility_obtain": 0,
      "tech_mobility_max": 0,
      "tech_mobility_120": 0,
      "tech_antisub_obtain": 0,
      "tech_antisub_max": 0,
      "tech_antisub_120": 0,
      "image_path": "images/specialized_bulin_mkiii.png"
    },
    {
      "id": 5,
      "name": "卡辛",
      "faction": "白鹰",
      "ship_class": "驱逐",
      "rarity": "普通",
      "owned": false,
      "breakthrough": 0,
      "can_remodel": true,
      "remodel_date": "2017-11-23",
      "remodeled": false,
      "oath": false,
      "level_120": false,
      "acquire_main": "轻型池建造、打捞、勋章支援概率获得",
      "acquire_detail": "下方仅列出普通掉落点",
      "build_time": "00:23:00（轻型池）",
      "drop_locations": [
        "1-3、1-4、2-1、2-2、2-3、3-2、3-3、3-4、4-3、4-4、7-1、7-2、8-1、8-2、8-3、8-4、12-1、12-2、12-3、12-4、13-1、13-2、13-3、13-4、14-1、14-2、14-3、14-4、15-1、15-2、15-3、15-3"
      ],
      "shop_exchange": "无",
      "is_permanent": true,
      "debut_event": "",
      "release_date": "2017-05-25",
      "notes": "",
      "tech_points_obtain": 2,
      "tech_points_max": 5,
      "tech_points_120": 4,
      "bonus_obtain": [],
      "bonus_120": [],
      "tech_affects": [
        "驱逐"
      ],
      "tech_durability_obtain": 1,
      "tech_durability_max": 0,
      "tech_durability_120": 1,
      "tech_firepower_obtain": 0,
      "tech_firepower_max": 0,
      "tech_firepower_120": 0,
      "tech_torpedo_obtain": 0,
      "tech_torpedo_max": 0,
      "tech_torpedo_120": 0,
      "tech_aa_obtain": 0,
      "tech_aa_max": 0,
      "tech_aa_120": 0,
      "tech_aviation_obtain": 0,
      "tech_aviation_max": 0,
      "tech_aviation_120": 0,
      "tech_accuracy_obtain": 0,
      "tech_accuracy_max": 0,
      "tech_accuracy_120": 0,
      "tech_reload_obtain": 0,
      "tech_reload_max": 0,
      "tech_reload_120": 0,
      "tech_mobility_obtain": 0,
      "tech_mobility_max": 0,
      "tech_mobility_120": 0,
      "tech_antisub_obtain": 0,
      "tech_antisub_max": 0,
      "tech_antisub_120": 0,
      "image_path": "images/cassin.png"
    },
    {
      "id": 6,
      "name": "唐斯",
      "faction": "白鹰",
      "ship_class": "驱逐",
      "rarity": "普通",
      "owned": false,
      "breakthrough": 0,
      "can_remodel": true,
      "remodel_date": "2017-11-23",
      "remodeled": false,
      "oath": false,
      "level_120": false,
      "acquire_main": "轻型池建造、打捞、勋章支援概率获得",
      "acquire_detail": "下方仅列出普通掉落点",
      "build_time": "00:23:00（轻型池）",
      "drop_locations": [
        "1-3、1-4、2-1、2-2、2-3、3-2、3-3、3-4、4-3、4-4、7-1、7-2、8-2、8-3、8-4、8-1、12-1、12-2、12-3、12-4、13-1、13-2、13-3、13-4、14-1、14-2、14-3、14-4、15-1、15-2、15-3、15-4、16-1、16-2、16-3、16-4"
      ],
      "shop_exchange": "",
      "is_permanent": true,
      "debut_event": "",
      "release_date": "2017-05-25",
      "notes": "",
      "tech_points_obtain": 2,
      "tech_points_max": 5,
      "tech_points_120": 4,
      "bonus_obtain": [],
      "bonus_120": [],
      "tech_affects": [
        "驱逐"
      ],
      "tech_durability_obtain": 1,
      "tech_durability_max": 0,
      "tech_durability_120": 1,
      "tech_firepower_obtain": 0,
      "tech_firepower_max": 0,
      "tech_firepower_120": 0,
      "tech_torpedo_obtain": 0,
      "tech_torpedo_max": 0,
      "tech_torpedo_120": 0,
      "tech_aa_obtain": 0,
      "tech_aa_max": 0,
      "tech_aa_120": 0,
      "tech_aviation_obtain": 0,
      "tech_aviation_max": 0,
      "tech_aviation_120": 0,
      "tech_accuracy_obtain": 0,
      "tech_accuracy_max": 0,
      "tech_accuracy_120": 0,
      "tech_reload_obtain": 0,
      "tech_reload_max": 0,
      "tech_reload_120": 0,
      "tech_mobility_obtain": 0,
      "tech_mobility_max": 0,
      "tech_mobility_120": 0,
      "tech_antisub_obtain": 0,
      "tech_antisub_max": 0,
      "tech_antisub_120": 0,
      "image_path": ""
    },
    {
      "id": 7,
      "name": "格里德利",
      "faction": "白鹰",
      "ship_class": "驱逐",
      "rarity": "稀有",
      "owned": false,
      "breakthrough": 0,
      "can_remodel": false,
      "remodel_date": "",
      "remodeled": false,
      "oath": false,
      "level_120": false,
      "acquire_main": "打捞、勋章支援概率获得",
      "acquire_detail": "下方仅列出普通掉落点",
      "build_time": "",
      "drop_locations": [
        "2-2、2-3、4-4、7-1、10-2、11-1、12-1、14-4、16-4"
      ],
      "shop_exchange": "",
      "is_permanent": true,
      "debut_event": "",
      "release_date": "2017-05-25",
      "notes": "",
      "tech_points_obtain": 4,
      "tech_points_max": 9,
      "tech_points_120": 7,
      "bonus_obtain": [],
      "bonus_120": [],
      "tech_affects": [
        "驱逐"
      ],
      "tech_durability_obtain": 1,
      "tech_durability_max": 0,
      "tech_durability_120": 0,
      "tech_firepower_obtain": 0,
      "tech_firepower_max": 0,
      "tech_firepower_120": 0,
      "tech_torpedo_obtain": 0,
      "tech_torpedo_max": 0,
      "tech_torpedo_120": 0,
      "tech_aa_obtain": 0,
      "tech_aa_max": 0,
      "tech_aa_120": 1,
      "tech_aviation_obtain": 0,
      "tech_aviation_max": 0,
      "tech_aviation_120": 0,
      "tech_accuracy_obtain": 0,
      "tech_accuracy_max": 0,
      "tech_accuracy_120": 0,
      "tech_reload_obtain": 0,
      "tech_reload_max": 0,
      "tech_reload_120": 0,
      "tech_mobility_obtain": 0,
      "tech_mobility_max": 0,
      "tech_mobility_120": 0,
      "tech_antisub_obtain": 0,
      "tech_antisub_max": 0,
      "tech_antisub_120": 0,
      "image_path": "image/gridley.png"
    },
    {
      "id": 4,
      "name": "杜威",
      "faction": "白鹰",
      "ship_class": "驱逐",
      "rarity": "稀有",
      "owned": false,
      "breakthrough": 0,
      "can_remodel": false,
      "remodel_date": "",
      "remodeled": false,
      "oath": false,
      "level_120": false,
      "acquire_main": "打捞",
      "acquire_detail": "仅限打捞",
      "build_time": "",
      "drop_locations": [
        "13-3、16-2"
      ],
      "shop_exchange": "",
      "is_permanent": true,
      "debut_event": "",
      "release_date": "2019-03-22",
      "notes": "",
      "tech_points_obtain": 3,
      "tech_points_max": 7,
      "tech_points_120": 5,
      "bonus_obtain": [],
      "bonus_120": [],
      "tech_affects": [
        "驱逐"
      ],
      "tech_durability_obtain": 1,
      "tech_durability_max": 0,
      "tech_durability_120": 1,
      "tech_firepower_obtain": 0,
      "tech_firepower_max": 0,
      "tech_firepower_120": 0,
      "tech_torpedo_obtain": 0,
      "tech_torpedo_max": 0,
      "tech_torpedo_120": 0,
      "tech_aa_obtain": 0,
      "tech_aa_max": 0,
      "tech_aa_120": 0,
      "tech_aviation_obtain": 0,
      "tech_aviation_max": 0,
      "tech_aviation_120": 0,
      "tech_accuracy_obtain": 0,
      "tech_accuracy_max": 0,
      "tech_accuracy_120": 0,
      "tech_reload_obtain": 0,
      "tech_reload_max": 0,
      "tech_reload_120": 0,
      "tech_mobility_obtain": 0,
      "tech_mobility_max": 0,
      "tech_mobility_120": 0,
      "tech_antisub_obtain": 0,
      "tech_antisub_max": 0,
      "tech_antisub_120": 0,
      "image_path": "image/dewey.png"
    },
    {
      "id": 406,
      "name": "艾尔温",
      "faction": "白鹰",
      "ship_class": "驱逐",
      "rarity": "稀有",
      "owned": false,
      "breakthrough": 0,
      "can_remodel": false,
      "remodel_date": "",
      "remodeled": false,
      "oath": false,
      "level_120": false,
      "acquire_main": "打捞",
      "acquire_detail": "作战档案打捞掉落",
      "build_time": "",
      "drop_locations": [
        "作战档案箱庭疗法：B1/B2/B3/D1/D2/D3"
      ],
      "shop_exchange": "",
      "is_permanent": true,
      "debut_event": "箱庭疗法",
      "release_date": "2019-07-31",
      "notes": "",
      "tech_points_obtain": 3,
      "tech_points_max": 7,
      "tech_points_120": 5,
      "bonus_obtain": [],
      "bonus_120": [],
      "tech_affects": [
        "驱逐"
      ],
      "tech_durability_obtain": 1,
      "tech_durability_max": 0,
      "tech_durability_120": 1,
      "tech_firepower_obtain": 0,
      "tech_firepower_max": 0,
      "tech_firepower_120": 0,
      "tech_torpedo_obtain": 0,
      "tech_torpedo_max": 0,
      "tech_torpedo_120": 0,
      "tech_aa_obtain": 0,
      "tech_aa_max": 0,
      "tech_aa_120": 0,
      "tech_aviation_obtain": 0,
      "tech_aviation_max": 0,
      "tech_aviation_120": 0,
      "tech_accuracy_obtain": 0,
      "tech_accuracy_max": 0,
      "tech_accuracy_120": 0,
      "tech_reload_obtain": 0,
      "tech_reload_max": 0,
      "tech_reload_120": 0,
      "tech_mobility_obtain": 0,
      "tech_mobility_max": 0,
      "tech_mobility_120": 0,
      "tech_antisub_obtain": 0,
      "tech_antisub_max": 0,
      "tech_antisub_120": 0,
      "image_path": ""
    },
    {
      "id": 8,
      "name": "克雷文",
      "faction": "白鹰",
      "ship_class": "驱逐",
      "rarity": "普通",
      "owned": false,
      "breakthrough": 0,
      "can_remodel": false,
      "remodel_date": "",
      "remodeled": false,
      "oath": false,
      "level_120": false,
      "acquire_main": "建造、打捞、勋章支援概率获得",
      "acquire_detail": "下方仅列出普通掉落点",
      "build_time": "00:25:00（轻型池）",
      "drop_locations": [
        "1-1、1-2、1-3、1-4、2-1、2-2、2-4、3-1、3-2、4-4、6-3、7-3、8-2、8-3、8-4、8-1、11-1、11-2、11-3、11-4"
      ],
      "shop_exchange": "",
      "is_permanent": true,
      "debut_event": "",
      "release_date": "2017-05-25",
      "notes": "",
      "tech_points_obtain": 3,
      "tech_points_max": 6,
      "tech_points_120": 4,
      "bonus_obtain": [],
      "bonus_120": [],
      "tech_affects": [
        "驱逐"
      ],
      "tech_durability_obtain": 1,
      "tech_durability_max": 0,
      "tech_durability_120": 1,
      "tech_firepower_obtain": 0,
      "tech_firepower_max": 0,
      "tech_firepower_120": 0,
      "tech_torpedo_obtain": 0,
      "tech_torpedo_max": 0,
      "tech_torpedo_120": 0,
      "tech_aa_obtain": 0,
      "tech_aa_max": 0,
      "tech_aa_120": 0,
      "tech_aviation_obtain": 0,
      "tech_aviation_max": 0,
      "tech_aviation_120": 0,
      "tech_accuracy_obtain": 0,
      "tech_accuracy_max": 0,
      "tech_accuracy_120": 0,
      "tech_reload_obtain": 0,
      "tech_reload_max": 0,
      "tech_reload_120": 0,
      "tech_mobility_obtain": 0,
      "tech_mobility_max": 0,
      "tech_mobility_120": 0,
      "tech_antisub_obtain": 0,
      "tech_antisub_max": 0,
      "tech_antisub_120": 0,
      "image_path": "image/craven.png"
    },
    {
      "id": 9,
      "name": "麦考尔",
      "faction": "白鹰",
      "ship_class": "驱逐",
      "rarity": "普通",
      "owned": false,
      "breakthrough": 0,
      "can_remodel": false,
      "remodel_date": "",
      "remodeled": false,
      "oath": false,
      "level_120": false,
      "acquire_main": "建造、打捞、勋章支援概率获得",
      "acquire_detail": "下方仅列出普通掉落点",
      "build_time": "00:25:00（轻型池）",
      "drop_locations": [
        "1-1、1-2、1-3、1-4、2-1、2-2、2-4、3-1、3-2、4-4、6-3、7-3、8-2、8-3、8-4、8-1、11-1、11-2、11-3、11-4、15-1、15-2、15-3、15-4、16-1、16-2、16-3、16-4"
      ],
      "shop_exchange": "",
      "is_permanent": true,
      "debut_event": "",
      "release_date": "2017-05-25",
      "notes": "",
      "tech_points_obtain": 3,
      "tech_points_max": 6,
      "tech_points_120": 4,
      "bonus_obtain": [],
      "bonus_120": [],
      "tech_affects": [
        "驱逐"
      ],
      "tech_durability_obtain": 1,
      "tech_durability_max": 0,
      "tech_durability_120": 1,
      "tech_firepower_obtain": 0,
      "tech_firepower_max": 0,
      "tech_firepower_120": 0,
      "tech_torpedo_obtain": 0,
      "tech_torpedo_max": 0,
      "tech_torpedo_120": 0,
      "tech_aa_obtain": 0,
      "tech_aa_max": 0,
      "tech_aa_120": 0,
      "tech_aviation_obtain": 0,
      "tech_aviation_max": 0,
      "tech_aviation_120": 0,
      "tech_accuracy_obtain": 0,
      "tech_accuracy_max": 0,
      "tech_accuracy_120": 0,
      "tech_reload_obtain": 0,
      "tech_reload_max": 0,
      "tech_reload_120": 0,
      "tech_mobility_obtain": 0,
      "tech_mobility_max": 0,
      "tech_mobility_120": 0,
      "tech_antisub_obtain": 0,
      "tech_antisub_max": 0,
      "tech_antisub_120": 0,
      "image_path": "image/mccall.png"
    },
    {
      "id": 10,
      "name": "莫里",
      "faction": "白鹰",
      "ship_class": "驱逐",
      "rarity": "精锐",
      "owned": false,
      "breakthrough": 0,
      "can_remodel": true,
      "remodel_date": "2025-12-18",
      "remodeled": false,
      "oath": false,
      "level_120": false,
      "acquire_main": "轻型池建造",
      "acquire_detail": "收藏奖励·格里德利级（获取后解锁建造）",
      "build_time": "00:25:00（轻型池）",
      "drop_locations": [],
      "shop_exchange": "",
      "is_permanent": true,
      "debut_event": "",
      "release_date": "2017-5-25",
      "notes": "",
      "tech_points_obtain": 6,
      "tech_points_max": 12,
      "tech_points_120": 9,
      "bonus_obtain": [],
      "bonus_120": [],
      "tech_affects": [
        "驱逐"
      ],
      "tech_durability_obtain": 1,
      "tech_durability_max": 0,
      "tech_durability_120": 0,
      "tech_firepower_obtain": 0,
      "tech_firepower_max": 0,
      "tech_firepower_120": 0,
      "tech_torpedo_obtain": 0,
      "tech_torpedo_max": 0,
      "tech_torpedo_120": 0,
      "tech_aa_obtain": 0,
      "tech_aa_max": 0,
      "tech_aa_120": 0,
      "tech_aviation_obtain": 0,
      "tech_aviation_max": 0,
      "tech_aviation_120": 0,
      "tech_accuracy_obtain": 0,
      "tech_accuracy_max": 0,
      "tech_accuracy_120": 0,
      "tech_reload_obtain": 0,
      "tech_reload_max": 0,
      "tech_reload_120": 0,
      "tech_mobility_obtain": 0,
      "tech_mobility_max": 0,
      "tech_mobility_120": 1,
      "tech_antisub_obtain": 0,
      "tech_antisub_max": 0,
      "tech_antisub_120": 0,
      "image_path": "image/maury.png"
    },
    {
      "id": 26,
      "name": "西姆斯",
      "faction": "白鹰",
      "ship_class": "驱逐",
      "rarity": "稀有",
      "owned": false,
      "breakthrough": 0,
      "can_remodel": true,
      "remodel_date": "2019-02-21",
      "remodeled": false,
      "oath": false,
      "level_120": false,
      "acquire_main": "打捞、勋章支援概率获得",
      "acquire_detail": "下方仅列出普通掉落点",
      "build_time": "",
      "drop_locations": [
        "3-2、4-1、7-3、7-4、10-3、11-1、12-2、14-2、15-4"
      ],
      "shop_exchange": "",
      "is_permanent": true,
      "debut_event": "",
      "release_date": "2017-5-25",
      "notes": "2019年8月15日09:00港区改建后无法通过建造获得",
      "tech_points_obtain": 5,
      "tech_points_max": 10,
      "tech_points_120": 8,
      "bonus_obtain": [],
      "bonus_120": [],
      "tech_affects": [
        "驱逐"
      ],
      "tech_durability_obtain": 1,
      "tech_durability_max": 0,
      "tech_durability_120": 0,
      "tech_firepower_obtain": 0,
      "tech_firepower_max": 0,
      "tech_firepower_120": 0,
      "tech_torpedo_obtain": 0,
      "tech_torpedo_max": 0,
      "tech_torpedo_120": 0,
      "tech_aa_obtain": 0,
      "tech_aa_max": 0,
      "tech_aa_120": 1,
      "tech_aviation_obtain": 0,
      "tech_aviation_max": 0,
      "tech_aviation_120": 0,
      "tech_accuracy_obtain": 0,
      "tech_accuracy_max": 0,
      "tech_accuracy_120": 0,
      "tech_reload_obtain": 0,
      "tech_reload_max": 0,
      "tech_reload_120": 0,
      "tech_mobility_obtain": 0,
      "tech_mobility_max": 0,
      "tech_mobility_120": 0,
      "tech_antisub_obtain": 0,
      "tech_antisub_max": 0,
      "tech_antisub_120": 0,
      "image_path": "image\\sims.png"
    },
    {
      "id": 27,
      "name": "哈曼",
      "faction": "白鹰",
      "ship_class": "驱逐",
      "rarity": "稀有",
      "owned": false,
      "breakthrough": 0,
      "can_remodel": true,
      "remodel_date": "2017-07-06",
      "remodeled": false,
      "oath": false,
      "level_120": false,
      "acquire_main": "轻型池建造、打捞、勋章支援概率获得",
      "acquire_detail": "下方仅列出普通掉落点",
      "build_time": "00:26:00（轻型池）",
      "drop_locations": [
        "3-2、4-1、7-3、7-4、10-3、11-1、12-2、14-1、16-4"
      ],
      "shop_exchange": "",
      "is_permanent": true,
      "debut_event": "",
      "release_date": "2017-05-25",
      "notes": "",
      "tech_points_obtain": 5,
      "tech_points_max": 10,
      "tech_points_120": 8,
      "bonus_obtain": [],
      "bonus_120": [],
      "tech_affects": [
        "驱逐"
      ],
      "tech_durability_obtain": 1,
      "tech_durability_max": 0,
      "tech_durability_120": 0,
      "tech_firepower_obtain": 0,
      "tech_firepower_max": 0,
      "tech_firepower_120": 0,
      "tech_torpedo_obtain": 0,
      "tech_torpedo_max": 0,
      "tech_torpedo_120": 0,
      "tech_aa_obtain": 0,
      "tech_aa_max": 0,
      "tech_aa_120": 1,
      "tech_aviation_obtain": 0,
      "tech_aviation_max": 0,
      "tech_aviation_120": 0,
      "tech_accuracy_obtain": 0,
      "tech_accuracy_max": 0,
      "tech_accuracy_120": 0,
      "tech_reload_obtain": 0,
      "tech_reload_max": 0,
      "tech_reload_120": 0,
      "tech_mobility_obtain": 0,
      "tech_mobility_max": 0,
      "tech_mobility_120": 0,
      "tech_antisub_obtain": 0,
      "tech_antisub_max": 0,
      "tech_antisub_120": 0,
      "image_path": ""
    },
    {
      "id": 18,
      "name": "本森",
      "faction": "白鹰",
      "ship_class": "驱逐",
      "rarity": "稀有",
      "owned": false,
      "breakthrough": 0,
      "can_remodel": false,
      "remodel_date": "",
      "remodeled": false,
      "oath": false,
      "level_120": false,
      "acquire_main": "月度签到、商店",
      "acquire_detail": "2017年6月签到",
      "build_time": "",
      "drop_locations": [],
      "shop_exchange": "舰队商店2000舰队币兑换",
      "is_permanent": true,
      "debut_event": "",
      "release_date": "2017-05-25",
      "notes": "",
      "tech_points_obtain": 6,
      "tech_points_max": 12,
      "tech_points_120": 9,
      "bonus_obtain": [],
      "bonus_120": [],
      "tech_affects": [
        "驱逐"
      ],
      "tech_durability_obtain": 1,
      "tech_durability_max": 0,
      "tech_durability_120": 0,
      "tech_firepower_obtain": 0,
      "tech_firepower_max": 0,
      "tech_firepower_120": 0,
      "tech_torpedo_obtain": 0,
      "tech_torpedo_max": 0,
      "tech_torpedo_120": 0,
      "tech_aa_obtain": 0,
      "tech_aa_max": 0,
      "tech_aa_120": 1,
      "tech_aviation_obtain": 0,
      "tech_aviation_max": 0,
      "tech_aviation_120": 0,
      "tech_accuracy_obtain": 0,
      "tech_accuracy_max": 0,
      "tech_accuracy_120": 0,
      "tech_reload_obtain": 0,
      "tech_reload_max": 0,
      "tech_reload_120": 0,
      "tech_mobility_obtain": 0,
      "tech_mobility_max": 0,
      "tech_mobility_120": 0,
      "tech_antisub_obtain": 0,
      "tech_antisub_max": 0,
      "tech_antisub_120": 0,
      "image_path": "image/benson.png"
    },
    {
      "id": 19,
      "name": "拉菲",
      "faction": "白鹰",
      "ship_class": "驱逐",
      "rarity": "精锐",
      "owned": false,
      "breakthrough": 0,
      "can_remodel": true,
      "remodel_date": "2018-03-29",
      "remodeled": false,
      "oath": false,
      "level_120": false,
      "acquire_main": "初始舰、轻型池建造、打捞",
      "acquire_detail": "下方仅列出普通掉落点",
      "build_time": "00:27:00（轻型池）",
      "drop_locations": [
        "2-1、2-2、2-3、2-4、3-1、3-2、3-3、3-4、4-1、4-2、4-3、4-4、5-1、5-2、5-3、5-4、6-1、6-2、6-3、6-4、7-1、7-2、7-3、7-4、8-2、8-3、8-4、8-1、9-1、9-2、9-3、9-4、10-1、10-2、10-3、10-4、11-1、11-2、11-3、11-4、12-1、12-2、12-3、12-4、13-1、13-2、13-3、13-4、15-1、15-2、15-3、15-4、16-1、16-2、16-3、16-4、14-1、14-2、14-3、14-4"
      ],
      "shop_exchange": "",
      "is_permanent": true,
      "debut_event": "",
      "release_date": "2017-05-25",
      "notes": "收藏奖励：主角队 所需船只,与Z23，标枪满破可获得绫波。",
      "tech_points_obtain": 8,
      "tech_points_max": 16,
      "tech_points_120": 12,
      "bonus_obtain": [],
      "bonus_120": [],
      "tech_affects": [
        "驱逐"
      ],
      "tech_durability_obtain": 1,
      "tech_durability_max": 0,
      "tech_durability_120": 0,
      "tech_firepower_obtain": 0,
      "tech_firepower_max": 0,
      "tech_firepower_120": 1,
      "tech_torpedo_obtain": 0,
      "tech_torpedo_max": 0,
      "tech_torpedo_120": 0,
      "tech_aa_obtain": 0,
      "tech_aa_max": 0,
      "tech_aa_120": 0,
      "tech_aviation_obtain": 0,
      "tech_aviation_max": 0,
      "tech_aviation_120": 0,
      "tech_accuracy_obtain": 0,
      "tech_accuracy_max": 0,
      "tech_accuracy_120": 0,
      "tech_reload_obtain": 0,
      "tech_reload_max": 0,
      "tech_reload_120": 0,
      "tech_mobility_obtain": 0,
      "tech_mobility_max": 0,
      "tech_mobility_120": 0,
      "tech_antisub_obtain": 0,
      "tech_antisub_max": 0,
      "tech_antisub_120": 0,
      "image_path": "image/laffey.png"
    },
    {
      "id": 263,
      "name": "贝利",
      "faction": "白鹰",
      "ship_class": "驱逐",
      "rarity": "稀有",
      "owned": false,
      "breakthrough": 0,
      "can_remodel": true,
      "remodel_date": "2018-01-19",
      "remodeled": false,
      "oath": false,
      "level_120": false,
      "acquire_main": "月度签到、商店兑换",
      "acquire_detail": "2017年7月签到",
      "build_time": "",
      "drop_locations": [],
      "shop_exchange": "舰队商店2000舰队币兑换",
      "is_permanent": true,
      "debut_event": "",
      "release_date": "2017-07-01",
      "notes": "",
      "tech_points_obtain": 6,
      "tech_points_max": 12,
      "tech_points_120": 9,
      "bonus_obtain": [],
      "bonus_120": [],
      "tech_affects": [
        "驱逐"
      ],
      "tech_durability_obtain": 1,
      "tech_durability_max": 0,
      "tech_durability_120": 0,
      "tech_firepower_obtain": 0,
      "tech_firepower_max": 0,
      "tech_firepower_120": 0,
      "tech_torpedo_obtain": 0,
      "tech_torpedo_max": 0,
      "tech_torpedo_120": 0,
      "tech_aa_obtain": 0,
      "tech_aa_max": 0,
      "tech_aa_120": 1,
      "tech_aviation_obtain": 0,
      "tech_aviation_max": 0,
      "tech_aviation_120": 0,
      "tech_accuracy_obtain": 0,
      "tech_accuracy_max": 0,
      "tech_accuracy_120": 0,
      "tech_reload_obtain": 0,
      "tech_reload_max": 0,
      "tech_reload_120": 0,
      "tech_mobility_obtain": 0,
      "tech_mobility_max": 0,
      "tech_mobility_120": 0,
      "tech_antisub_obtain": 0,
      "tech_antisub_max": 0,
      "tech_antisub_120": 0,
      "image_path": "image\\bailey.png"
    },
    {
      "id": 362,
      "name": "霍比",
      "faction": "白鹰",
      "ship_class": "驱逐",
      "rarity": "稀有",
      "owned": false,
      "breakthrough": 0,
      "can_remodel": false,
      "remodel_date": "",
      "remodeled": false,
      "oath": false,
      "level_120": false,
      "acquire_main": "轻型池建造、作战补给",
      "acquire_detail": "复刻 战斗之星 作战补给（已过期）",
      "build_time": "00:27:00（轻型池）",
      "drop_locations": [],
      "shop_exchange": "",
      "is_permanent": true,
      "debut_event": "复刻 坠落之翼",
      "release_date": "2018-10-25",
      "notes": "",
      "tech_points_obtain": 6,
      "tech_points_max": 12,
      "tech_points_120": 9,
      "bonus_obtain": [],
      "bonus_120": [],
      "tech_affects": [
        "驱逐"
      ],
      "tech_durability_obtain": 1,
      "tech_durability_max": 0,
      "tech_durability_120": 0,
      "tech_firepower_obtain": 0,
      "tech_firepower_max": 0,
      "tech_firepower_120": 0,
      "tech_torpedo_obtain": 0,
      "tech_torpedo_max": 0,
      "tech_torpedo_120": 0,
      "tech_aa_obtain": 0,
      "tech_aa_max": 0,
      "tech_aa_120": 1,
      "tech_aviation_obtain": 0,
      "tech_aviation_max": 0,
      "tech_aviation_120": 0,
      "tech_accuracy_obtain": 0,
      "tech_accuracy_max": 0,
      "tech_accuracy_120": 0,
      "tech_reload_obtain": 0,
      "tech_reload_max": 0,
      "tech_reload_120": 0,
      "tech_mobility_obtain": 0,
      "tech_mobility_max": 0,
      "tech_mobility_120": 0,
      "tech_antisub_obtain": 0,
      "tech_antisub_max": 0,
      "tech_antisub_120": 0,
      "image_path": "image/hobby.png"
    },
    {
      "id": 363,
      "name": "科尔克",
      "faction": "白鹰",
      "ship_class": "驱逐",
      "rarity": "稀有",
      "owned": false,
      "breakthrough": 0,
      "can_remodel": false,
      "remodel_date": "",
      "remodeled": false,
      "oath": false,
      "level_120": false,
      "acquire_main": "轻型池建造",
      "acquire_detail": "",
      "build_time": "00:27:00（轻型池）",
      "drop_locations": [],
      "shop_exchange": "",
      "is_permanent": true,
      "debut_event": "复刻 坠落之翼",
      "release_date": "2018-10-25",
      "notes": "",
      "tech_points_obtain": 6,
      "tech_points_max": 12,
      "tech_points_120": 9,
      "bonus_obtain": [],
      "bonus_120": [],
      "tech_affects": [
        "驱逐"
      ],
      "tech_durability_obtain": 1,
      "tech_durability_max": 0,
      "tech_durability_120": 0,
      "tech_firepower_obtain": 0,
      "tech_firepower_max": 0,
      "tech_firepower_120": 0,
      "tech_torpedo_obtain": 0,
      "tech_torpedo_max": 0,
      "tech_torpedo_120": 0,
      "tech_aa_obtain": 0,
      "tech_aa_max": 0,
      "tech_aa_120": 1,
      "tech_aviation_obtain": 0,
      "tech_aviation_max": 0,
      "tech_aviation_120": 0,
      "tech_accuracy_obtain": 0,
      "tech_accuracy_max": 0,
      "tech_accuracy_120": 0,
      "tech_reload_obtain": 0,
      "tech_reload_max": 0,
      "tech_reload_120": 0,
      "tech_mobility_obtain": 0,
      "tech_mobility_max": 0,
      "tech_mobility_120": 0,
      "tech_antisub_obtain": 0,
      "tech_antisub_max": 0,
      "tech_antisub_120": 0,
      "image_path": "image/kalk.png"
    },
    {
      "id": 11,
      "name": "弗莱彻",
      "faction": "白鹰",
      "ship_class": "驱逐",
      "rarity": "稀有",
      "owned": false,
      "breakthrough": 0,
      "can_remodel": false,
      "remodel_date": "",
      "remodeled": false,
      "oath": false,
      "level_120": false,
      "acquire_main": "轻型池建造、打捞、商店兑换、勋章支援概率获得",
      "acquire_detail": "下方仅列出普通掉落点",
      "build_time": "00:28:00（轻型池）",
      "drop_locations": [
        "2-3、3-4、6-1、7-1、9-1、11-1、12-1、14-1、15-3、16-2"
      ],
      "shop_exchange": "舰队商店300舰队币兑换",
      "is_permanent": true,
      "debut_event": "",
      "release_date": "2017-05-25",
      "notes": "",
      "tech_points_obtain": 6,
      "tech_points_max": 13,
      "tech_points_120": 9,
      "bonus_obtain": [],
      "bonus_120": [],
      "tech_affects": [
        "驱逐"
      ],
      "tech_durability_obtain": 1,
      "tech_durability_max": 0,
      "tech_durability_120": 0,
      "tech_firepower_obtain": 0,
      "tech_firepower_max": 0,
      "tech_firepower_120": 0,
      "tech_torpedo_obtain": 0,
      "tech_torpedo_max": 0,
      "tech_torpedo_120": 0,
      "tech_aa_obtain": 0,
      "tech_aa_max": 0,
      "tech_aa_120": 1,
      "tech_aviation_obtain": 0,
      "tech_aviation_max": 0,
      "tech_aviation_120": 0,
      "tech_accuracy_obtain": 0,
      "tech_accuracy_max": 0,
      "tech_accuracy_120": 0,
      "tech_reload_obtain": 0,
      "tech_reload_max": 0,
      "tech_reload_120": 0,
      "tech_mobility_obtain": 0,
      "tech_mobility_max": 0,
      "tech_mobility_120": 0,
      "tech_antisub_obtain": 0,
      "tech_antisub_max": 0,
      "tech_antisub_120": 0,
      "image_path": "image/fletcher.png"
    },
    {
      "id": 299,
      "name": "拉德福特",
      "faction": "白鹰",
      "ship_class": "驱逐",
      "rarity": "稀有",
      "owned": false,
      "breakthrough": 0,
      "can_remodel": false,
      "remodel_date": "",
      "remodeled": false,
      "oath": false,
      "level_120": false,
      "acquire_main": "打捞",
      "acquire_detail": "仅限打捞",
      "build_time": "",
      "drop_locations": [
        "9-2"
      ],
      "shop_exchange": "",
      "is_permanent": true,
      "debut_event": "",
      "release_date": "2017-09-20",
      "notes": "",
      "tech_points_obtain": 6,
      "tech_points_max": 13,
      "tech_points_120": 9,
      "bonus_obtain": [],
      "bonus_120": [],
      "tech_affects": [
        "驱逐"
      ],
      "tech_durability_obtain": 1,
      "tech_durability_max": 0,
      "tech_durability_120": 0,
      "tech_firepower_obtain": 0,
      "tech_firepower_max": 0,
      "tech_firepower_120": 0,
      "tech_torpedo_obtain": 0,
      "tech_torpedo_max": 0,
      "tech_torpedo_120": 0,
      "tech_aa_obtain": 0,
      "tech_aa_max": 0,
      "tech_aa_120": 1,
      "tech_aviation_obtain": 0,
      "tech_aviation_max": 0,
      "tech_aviation_120": 0,
      "tech_accuracy_obtain": 0,
      "tech_accuracy_max": 0,
      "tech_accuracy_120": 0,
      "tech_reload_obtain": 0,
      "tech_reload_max": 0,
      "tech_reload_120": 0,
      "tech_mobility_obtain": 0,
      "tech_mobility_max": 0,
      "tech_mobility_120": 0,
      "tech_antisub_obtain": 0,
      "tech_antisub_max": 0,
      "tech_antisub_120": 0,
      "image_path": "image/radford.png"
    },
    {
      "id": 300,
      "name": "杰金斯",
      "faction": "白鹰",
      "ship_class": "驱逐",
      "rarity": "稀有",
      "owned": false,
      "breakthrough": 0,
      "can_remodel": false,
      "remodel_date": "",
      "remodeled": false,
      "oath": false,
      "level_120": false,
      "acquire_main": "打捞",
      "acquire_detail": "仅限打捞",
      "build_time": "",
      "drop_locations": [
        "9-2、15-3"
      ],
      "shop_exchange": "",
      "is_permanent": true,
      "debut_event": "",
      "release_date": "2017-09-20",
      "notes": "",
      "tech_points_obtain": 6,
      "tech_points_max": 13,
      "tech_points_120": 9,
      "bonus_obtain": [],
      "bonus_120": [],
      "tech_affects": [
        "驱逐"
      ],
      "tech_durability_obtain": 1,
      "tech_durability_max": 0,
      "tech_durability_120": 0,
      "tech_firepower_obtain": 0,
      "tech_firepower_max": 0,
      "tech_firepower_120": 0,
      "tech_torpedo_obtain": 0,
      "tech_torpedo_max": 0,
      "tech_torpedo_120": 0,
      "tech_aa_obtain": 0,
      "tech_aa_max": 0,
      "tech_aa_120": 1,
      "tech_aviation_obtain": 0,
      "tech_aviation_max": 0,
      "tech_aviation_120": 0,
      "tech_accuracy_obtain": 0,
      "tech_accuracy_max": 0,
      "tech_accuracy_120": 0,
      "tech_reload_obtain": 0,
      "tech_reload_max": 0,
      "tech_reload_120": 0,
      "tech_mobility_obtain": 0,
      "tech_mobility_max": 0,
      "tech_mobility_120": 0,
      "tech_antisub_obtain": 0,
      "tech_antisub_max": 0,
      "tech_antisub_120": 0,
      "image_path": "image/jenkins.png"
    },
    {
      "id": 301,
      "name": "尼古拉斯",
      "faction": "白鹰",
      "ship_class": "驱逐",
      "rarity": "精锐",
      "owned": false,
      "breakthrough": 0,
      "can_remodel": true,
      "remodel_date": "2018-07-17",
      "remodeled": false,
      "oath": false,
      "level_120": false,
      "acquire_main": "打捞",
      "acquire_detail": "仅限打捞",
      "build_time": "",
      "drop_locations": [
        "9-3"
      ],
      "shop_exchange": "",
      "is_permanent": true,
      "debut_event": "",
      "release_date": "2017-09-20",
      "notes": "",
      "tech_points_obtain": 8,
      "tech_points_max": 17,
      "tech_points_120": 13,
      "bonus_obtain": [],
      "bonus_120": [],
      "tech_affects": [
        "驱逐"
      ],
      "tech_durability_obtain": 1,
      "tech_durability_max": 0,
      "tech_durability_120": 0,
      "tech_firepower_obtain": 0,
      "tech_firepower_max": 0,
      "tech_firepower_120": 1,
      "tech_torpedo_obtain": 0,
      "tech_torpedo_max": 0,
      "tech_torpedo_120": 0,
      "tech_aa_obtain": 0,
      "tech_aa_max": 0,
      "tech_aa_120": 0,
      "tech_aviation_obtain": 0,
      "tech_aviation_max": 0,
      "tech_aviation_120": 0,
      "tech_accuracy_obtain": 0,
      "tech_accuracy_max": 0,
      "tech_accuracy_120": 0,
      "tech_reload_obtain": 0,
      "tech_reload_max": 0,
      "tech_reload_120": 0,
      "tech_mobility_obtain": 0,
      "tech_mobility_max": 0,
      "tech_mobility_120": 0,
      "tech_antisub_obtain": 0,
      "tech_antisub_max": 0,
      "tech_antisub_120": 0,
      "image_path": "image/nicholas.png"
    },
    {
      "id": 407,
      "name": "贝奇",
      "faction": "白鹰",
      "ship_class": "驱逐",
      "rarity": "稀有",
      "owned": false,
      "breakthrough": 0,
      "can_remodel": false,
      "remodel_date": "",
      "remodeled": false,
      "oath": false,
      "level_120": false,
      "acquire_main": "轻型池建造",
      "acquire_detail": "",
      "build_time": "00:28:00（轻型池）",
      "drop_locations": [],
      "shop_exchange": "",
      "is_permanent": true,
      "debut_event": "",
      "release_date": "2019-08-29",
      "notes": "",
      "tech_points_obtain": 6,
      "tech_points_max": 13,
      "tech_points_120": 9,
      "bonus_obtain": [],
      "bonus_120": [],
      "tech_affects": [
        "驱逐"
      ],
      "tech_durability_obtain": 1,
      "tech_durability_max": 0,
      "tech_durability_120": 0,
      "tech_firepower_obtain": 0,
      "tech_firepower_max": 0,
      "tech_firepower_120": 0,
      "tech_torpedo_obtain": 0,
      "tech_torpedo_max": 0,
      "tech_torpedo_120": 0,
      "tech_aa_obtain": 0,
      "tech_aa_max": 0,
      "tech_aa_120": 1,
      "tech_aviation_obtain": 0,
      "tech_aviation_max": 0,
      "tech_aviation_120": 0,
      "tech_accuracy_obtain": 0,
      "tech_accuracy_max": 0,
      "tech_accuracy_120": 0,
      "tech_reload_obtain": 0,
      "tech_reload_max": 0,
      "tech_reload_120": 0,
      "tech_mobility_obtain": 0,
      "tech_mobility_max": 0,
      "tech_mobility_120": 0,
      "tech_antisub_obtain": 0,
      "tech_antisub_max": 0,
      "tech_antisub_120": 0,
      "image_path": "image/bache.png"
    },
    {
      "id": 409,
      "name": "斯坦利",
      "faction": "白鹰",
      "ship_class": "驱逐",
      "rarity": "稀有",
      "owned": false,
      "breakthrough": 0,
      "can_remodel": false,
      "remodel_date": "",
      "remodeled": false,
      "oath": false,
      "level_120": false,
      "acquire_main": "轻型池建造、活动赠送",
      "acquire_detail": "限时活动 神圣的序幕 累计登录14天（过期）",
      "build_time": "00:28:00（轻型池）",
      "drop_locations": [],
      "shop_exchange": "",
      "is_permanent": true,
      "debut_event": "特别奖励登陆活动",
      "release_date": "2019-09-05",
      "notes": "",
      "tech_points_obtain": 6,
      "tech_points_max": 13,
      "tech_points_120": 9,
      "bonus_obtain": [],
      "bonus_120": [],
      "tech_affects": [
        "驱逐"
      ],
      "tech_durability_obtain": 1,
      "tech_durability_max": 0,
      "tech_durability_120": 0,
      "tech_firepower_obtain": 0,
      "tech_firepower_max": 0,
      "tech_firepower_120": 0,
      "tech_torpedo_obtain": 0,
      "tech_torpedo_max": 0,
      "tech_torpedo_120": 0,
      "tech_aa_obtain": 0,
      "tech_aa_max": 0,
      "tech_aa_120": 1,
      "tech_aviation_obtain": 0,
      "tech_aviation_max": 0,
      "tech_aviation_120": 0,
      "tech_accuracy_obtain": 0,
      "tech_accuracy_max": 0,
      "tech_accuracy_120": 0,
      "tech_reload_obtain": 0,
      "tech_reload_max": 0,
      "tech_reload_120": 0,
      "tech_mobility_obtain": 0,
      "tech_mobility_max": 0,
      "tech_mobility_120": 0,
      "tech_antisub_obtain": 0,
      "tech_antisub_max": 0,
      "tech_antisub_120": 0,
      "image_path": "image/stanly.png"
    },
    {
      "id": 16,
      "name": "富特",
      "faction": "白鹰",
      "ship_class": "驱逐",
      "rarity": "普通",
      "owned": false,
      "breakthrough": 0,
      "can_remodel": false,
      "remodel_date": "",
      "remodeled": false,
      "oath": false,
      "level_120": false,
      "acquire_main": "轻型池建造、打捞、勋章支援概率获得",
      "acquire_detail": "下方仅列出普通掉落点",
      "build_time": "00:28:00（轻型池）",
      "drop_locations": [
        "1-2、1-3、1-4、2-3、2-4、3-1、3-3、3-4、4-2、5-2、6-1、6-2、6-4、7-3、7-4、9-1、9-2、9-3、9-4、13-1、13-2、13-3、13-4、14-1、14-2、14-3、14-4、15-1、15-2、15-3、15-4"
      ],
      "shop_exchange": "",
      "is_permanent": true,
      "debut_event": "",
      "release_date": "2017-05-25",
      "notes": "收藏奖励：小海狸中队 所需船只",
      "tech_points_obtain": 4,
      "tech_points_max": 8,
      "tech_points_120": 6,
      "bonus_obtain": [],
      "bonus_120": [],
      "tech_affects": [
        "驱逐"
      ],
      "tech_durability_obtain": 1,
      "tech_durability_max": 0,
      "tech_durability_120": 1,
      "tech_firepower_obtain": 0,
      "tech_firepower_max": 0,
      "tech_firepower_120": 0,
      "tech_torpedo_obtain": 0,
      "tech_torpedo_max": 0,
      "tech_torpedo_120": 0,
      "tech_aa_obtain": 0,
      "tech_aa_max": 0,
      "tech_aa_120": 0,
      "tech_aviation_obtain": 0,
      "tech_aviation_max": 0,
      "tech_aviation_120": 0,
      "tech_accuracy_obtain": 0,
      "tech_accuracy_max": 0,
      "tech_accuracy_120": 0,
      "tech_reload_obtain": 0,
      "tech_reload_max": 0,
      "tech_reload_120": 0,
      "tech_mobility_obtain": 0,
      "tech_mobility_max": 0,
      "tech_mobility_120": 0,
      "tech_antisub_obtain": 0,
      "tech_antisub_max": 0,
      "tech_antisub_120": 0,
      "image_path": "image/foote.png"
    },
    {
      "id": 17,
      "name": "斯彭斯",
      "faction": "白鹰",
      "ship_class": "驱逐",
      "rarity": "普通",
      "owned": false,
      "breakthrough": 0,
      "can_remodel": false,
      "remodel_date": "",
      "remodeled": false,
      "oath": false,
      "level_120": false,
      "acquire_main": "轻型池建造、打捞、勋章支援概率获得",
      "acquire_detail": "下方仅列出普通掉落点",
      "build_time": "00:28:00（轻型池）",
      "drop_locations": [
        "1-2、1-3、1-4、2-3、2-4、3-1、3-3、3-4、4-2、5-2、6-1、6-2、6-4、7-3、7-4、9-1、9-2、9-3、9-4、13-1、13-2、13-3、13-4、16-1、16-2、16-3、16-4"
      ],
      "shop_exchange": "",
      "is_permanent": true,
      "debut_event": "",
      "release_date": "2017-05-25",
      "notes": "收藏奖励：小海狸中队 所需船只",
      "tech_points_obtain": 4,
      "tech_points_max": 8,
      "tech_points_120": 6,
      "bonus_obtain": [],
      "bonus_120": [],
      "tech_affects": [
        "驱逐"
      ],
      "tech_durability_obtain": 1,
      "tech_durability_max": 0,
      "tech_durability_120": 1,
      "tech_firepower_obtain": 0,
      "tech_firepower_max": 0,
      "tech_firepower_120": 0,
      "tech_torpedo_obtain": 0,
      "tech_torpedo_max": 0,
      "tech_torpedo_120": 0,
      "tech_aa_obtain": 0,
      "tech_aa_max": 0,
      "tech_aa_120": 0,
      "tech_aviation_obtain": 0,
      "tech_aviation_max": 0,
      "tech_aviation_120": 0,
      "tech_accuracy_obtain": 0,
      "tech_accuracy_max": 0,
      "tech_accuracy_120": 0,
      "tech_reload_obtain": 0,
      "tech_reload_max": 0,
      "tech_reload_120": 0,
      "tech_mobility_obtain": 0,
      "tech_mobility_max": 0,
      "tech_mobility_120": 0,
      "tech_antisub_obtain": 0,
      "tech_antisub_max": 0,
      "tech_antisub_120": 0,
      "image_path": "image/spence.png"
    },
    {
      "id": 14,
      "name": "撒切尔",
      "faction": "白鹰",
      "ship_class": "驱逐",
      "rarity": "稀有",
      "owned": false,
      "breakthrough": 0,
      "can_remodel": false,
      "remodel_date": "",
      "remodeled": false,
      "oath": false,
      "level_120": false,
      "acquire_main": "打捞、勋章支援概率获得",
      "acquire_detail": "下方仅列出普通掉落点",
      "build_time": "",
      "drop_locations": [
        "2-3、3-4、4-2、6-1、9-1、10-4、12-1、14-3、15-2、16-1"
      ],
      "shop_exchange": "",
      "is_permanent": true,
      "debut_event": "",
      "release_date": "2017-05-25",
      "notes": "",
      "tech_points_obtain": 6,
      "tech_points_max": 13,
      "tech_points_120": 9,
      "bonus_obtain": [],
      "bonus_120": [],
      "tech_affects": [
        "驱逐"
      ],
      "tech_durability_obtain": 1,
      "tech_durability_max": 0,
      "tech_durability_120": 0,
      "tech_firepower_obtain": 0,
      "tech_firepower_max": 0,
      "tech_firepower_120": 0,
      "tech_torpedo_obtain": 0,
      "tech_torpedo_max": 0,
      "tech_torpedo_120": 0,
      "tech_aa_obtain": 0,
      "tech_aa_max": 0,
      "tech_aa_120": 1,
      "tech_aviation_obtain": 0,
      "tech_aviation_max": 0,
      "tech_aviation_120": 0,
      "tech_accuracy_obtain": 0,
      "tech_accuracy_max": 0,
      "tech_accuracy_120": 0,
      "tech_reload_obtain": 0,
      "tech_reload_max": 0,
      "tech_reload_120": 0,
      "tech_mobility_obtain": 0,
      "tech_mobility_max": 0,
      "tech_mobility_120": 0,
      "tech_antisub_obtain": 0,
      "tech_antisub_max": 0,
      "tech_antisub_120": 0,
      "image_path": "image/thathcer.png"
    },
    {
      "id": 374,
      "name": "金伯利",
      "faction": "白鹰",
      "ship_class": "驱逐",
      "rarity": "稀有",
      "owned": false,
      "breakthrough": 0,
      "can_remodel": false,
      "remodel_date": "",
      "remodeled": false,
      "oath": false,
      "level_120": false,
      "acquire_main": "商店兑换、勋章支援概率获得",
      "acquire_detail": "舰队商店兑换",
      "build_time": "",
      "drop_locations": [],
      "shop_exchange": "舰队商店300舰队币兑换",
      "is_permanent": true,
      "debut_event": "闹腾嬉戏东煌春节",
      "release_date": "2019-01-31",
      "notes": "",
      "tech_points_obtain": 6,
      "tech_points_max": 13,
      "tech_points_120": 9,
      "bonus_obtain": [],
      "bonus_120": [],
      "tech_affects": [
        "驱逐"
      ],
      "tech_durability_obtain": 1,
      "tech_durability_max": 0,
      "tech_durability_120": 0,
      "tech_firepower_obtain": 0,
      "tech_firepower_max": 0,
      "tech_firepower_120": 0,
      "tech_torpedo_obtain": 0,
      "tech_torpedo_max": 0,
      "tech_torpedo_120": 0,
      "tech_aa_obtain": 0,
      "tech_aa_max": 0,
      "tech_aa_120": 1,
      "tech_aviation_obtain": 0,
      "tech_aviation_max": 0,
      "tech_aviation_120": 0,
      "tech_accuracy_obtain": 0,
      "tech_accuracy_max": 0,
      "tech_accuracy_120": 0,
      "tech_reload_obtain": 0,
      "tech_reload_max": 0,
      "tech_reload_120": 0,
      "tech_mobility_obtain": 0,
      "tech_mobility_max": 0,
      "tech_mobility_120": 0,
      "tech_antisub_obtain": 0,
      "tech_antisub_max": 0,
      "tech_antisub_120": 0,
      "image_path": "image/kimberly.png"
    },
    {
      "id": 375,
      "name": "马拉尼",
      "faction": "白鹰",
      "ship_class": "驱逐",
      "rarity": "精锐",
      "owned": false,
      "breakthrough": 0,
      "can_remodel": false,
      "remodel_date": "",
      "remodeled": false,
      "oath": false,
      "level_120": false,
      "acquire_main": "商店兑换、勋章支援概率获得",
      "acquire_detail": "",
      "build_time": "",
      "drop_locations": [],
      "shop_exchange": "舰队商店800舰队币兑换",
      "is_permanent": true,
      "debut_event": "闹腾嬉戏东煌春节",
      "release_date": "2019-01-31",
      "notes": "",
      "tech_points_obtain": 8,
      "tech_points_max": 17,
      "tech_points_120": 13,
      "bonus_obtain": [],
      "bonus_120": [],
      "tech_affects": [
        "驱逐"
      ],
      "tech_durability_obtain": 1,
      "tech_durability_max": 0,
      "tech_durability_120": 0,
      "tech_firepower_obtain": 0,
      "tech_firepower_max": 0,
      "tech_firepower_120": 0,
      "tech_torpedo_obtain": 0,
      "tech_torpedo_max": 0,
      "tech_torpedo_120": 0,
      "tech_aa_obtain": 0,
      "tech_aa_max": 0,
      "tech_aa_120": 1,
      "tech_aviation_obtain": 0,
      "tech_aviation_max": 0,
      "tech_aviation_120": 0,
      "tech_accuracy_obtain": 0,
      "tech_accuracy_max": 0,
      "tech_accuracy_120": 0,
      "tech_reload_obtain": 0,
      "tech_reload_max": 0,
      "tech_reload_120": 0,
      "tech_mobility_obtain": 0,
      "tech_mobility_max": 0,
      "tech_mobility_120": 0,
      "tech_antisub_obtain": 0,
      "tech_antisub_max": 0,
      "tech_antisub_120": 0,
      "image_path": "image/mullany"
    },
    {
      "id": 355,
      "name": "布什",
      "faction": "白鹰",
      "ship_class": "驱逐",
      "rarity": "稀有",
      "owned": false,
      "breakthrough": 0,
      "can_remodel": false,
      "remodel_date": "",
      "remodeled": false,
      "oath": false,
      "level_120": false,
      "acquire_main": "月度签到、商店兑换",
      "acquire_detail": "",
      "build_time": "无法建造",
      "drop_locations": [],
      "shop_exchange": "舰队商店2000舰队币兑换",
      "is_permanent": true,
      "debut_event": "",
      "release_date": "2018-08-01",
      "notes": "2019年5月9日09:00港区改建轻型建造常驻，后移出",
      "tech_points_obtain": 6,
      "tech_points_max": 13,
      "tech_points_120": 9,
      "bonus_obtain": [],
      "bonus_120": [],
      "tech_affects": [
        "驱逐"
      ],
      "tech_durability_obtain": 1,
      "tech_durability_max": 0,
      "tech_durability_120": 0,
      "tech_firepower_obtain": 0,
      "tech_firepower_max": 0,
      "tech_firepower_120": 0,
      "tech_torpedo_obtain": 0,
      "tech_torpedo_max": 0,
      "tech_torpedo_120": 0,
      "tech_aa_obtain": 0,
      "tech_aa_max": 0,
      "tech_aa_120": 1,
      "tech_aviation_obtain": 0,
      "tech_aviation_max": 0,
      "tech_aviation_120": 0,
      "tech_accuracy_obtain": 0,
      "tech_accuracy_max": 0,
      "tech_accuracy_120": 0,
      "tech_reload_obtain": 0,
      "tech_reload_max": 0,
      "tech_reload_120": 0,
      "tech_mobility_obtain": 0,
      "tech_mobility_max": 0,
      "tech_mobility_120": 0,
      "tech_antisub_obtain": 0,
      "tech_antisub_max": 0,
      "tech_antisub_120": 0,
      "image_path": "image/bush.png"
    },
    {
      "id": 365,
      "name": "黑泽伍德",
      "faction": "白鹰",
      "ship_class": "驱逐",
      "rarity": "稀有",
      "owned": false,
      "breakthrough": 0,
      "can_remodel": false,
      "remodel_date": "",
      "remodeled": false,
      "oath": false,
      "level_120": false,
      "acquire_main": "月度签到、商店兑换",
      "acquire_detail": "2018年11月签到",
      "build_time": "无法建造",
      "drop_locations": [],
      "shop_exchange": "舰队商店2000舰队币兑换",
      "is_permanent": true,
      "debut_event": "",
      "release_date": "2026-03-15",
      "notes": "炸服少女，实装当天服务器故障。",
      "tech_points_obtain": 6,
      "tech_points_max": 13,
      "tech_points_120": 9,
      "bonus_obtain": [],
      "bonus_120": [],
      "tech_affects": [
        "驱逐"
      ],
      "tech_durability_obtain": 1,
      "tech_durability_max": 0,
      "tech_durability_120": 0,
      "tech_firepower_obtain": 0,
      "tech_firepower_max": 0,
      "tech_firepower_120": 0,
      "tech_torpedo_obtain": 0,
      "tech_torpedo_max": 0,
      "tech_torpedo_120": 0,
      "tech_aa_obtain": 0,
      "tech_aa_max": 0,
      "tech_aa_120": 1,
      "tech_aviation_obtain": 0,
      "tech_aviation_max": 0,
      "tech_aviation_120": 0,
      "tech_accuracy_obtain": 0,
      "tech_accuracy_max": 0,
      "tech_accuracy_120": 0,
      "tech_reload_obtain": 0,
      "tech_reload_max": 0,
      "tech_reload_120": 0,
      "tech_mobility_obtain": 0,
      "tech_mobility_max": 0,
      "tech_mobility_120": 0,
      "tech_antisub_obtain": 0,
      "tech_antisub_max": 0,
      "tech_antisub_120": 0,
      "image_path": "image/hazelwood.png"
    },
    {
      "id": 684,
      "name": "米勒",
      "faction": "白鹰",
      "ship_class": "驱逐",
      "rarity": "精锐",
      "owned": false,
      "breakthrough": 0,
      "can_remodel": false,
      "remodel_date": "",
      "remodeled": false,
      "oath": false,
      "level_120": false,
      "acquire_main": "建造",
      "acquire_detail": "深谷来信期间限定建造",
      "build_time": "00:28:00（期间限定）",
      "drop_locations": [],
      "shop_exchange": "",
      "is_permanent": false,
      "debut_event": "深谷来信",
      "release_date": "2025-03-27",
      "notes": "",
      "tech_points_obtain": 8,
      "tech_points_max": 17,
      "tech_points_120": 13,
      "bonus_obtain": [],
      "bonus_120": [],
      "tech_affects": [
        "驱逐"
      ],
      "tech_durability_obtain": 1,
      "tech_durability_max": 0,
      "tech_durability_120": 0,
      "tech_firepower_obtain": 0,
      "tech_firepower_max": 0,
      "tech_firepower_120": 0,
      "tech_torpedo_obtain": 0,
      "tech_torpedo_max": 0,
      "tech_torpedo_120": 0,
      "tech_aa_obtain": 0,
      "tech_aa_max": 0,
      "tech_aa_120": 1,
      "tech_aviation_obtain": 0,
      "tech_aviation_max": 0,
      "tech_aviation_120": 0,
      "tech_accuracy_obtain": 0,
      "tech_accuracy_max": 0,
      "tech_accuracy_120": 0,
      "tech_reload_obtain": 0,
      "tech_reload_max": 0,
      "tech_reload_120": 0,
      "tech_mobility_obtain": 0,
      "tech_mobility_max": 0,
      "tech_mobility_120": 0,
      "tech_antisub_obtain": 0,
      "tech_antisub_max": 0,
      "tech_antisub_120": 0,
      "image_path": "image/miller.png"
    },
    {
      "id": 509,
      "name": "史蒂芬·波特",
      "faction": "白鹰",
      "ship_class": "驱逐",
      "rarity": "精锐",
      "owned": false,
      "breakthrough": 0,
      "can_remodel": false,
      "remodel_date": "",
      "remodeled": false,
      "oath": false,
      "level_120": false,
      "acquire_main": "商店兑换、勋章支援概率获得",
      "acquire_detail": "",
      "build_time": "无法建造",
      "drop_locations": [],
      "shop_exchange": "舰队商店800舰队币兑换",
      "is_permanent": true,
      "debut_event": "复刻:箱庭疗法",
      "release_date": "2021-03-25",
      "notes": "",
      "tech_points_obtain": 8,
      "tech_points_max": 17,
      "tech_points_120": 13,
      "bonus_obtain": [],
      "bonus_120": [],
      "tech_affects": [
        "驱逐"
      ],
      "tech_durability_obtain": 1,
      "tech_durability_max": 0,
      "tech_durability_120": 1,
      "tech_firepower_obtain": 0,
      "tech_firepower_max": 0,
      "tech_firepower_120": 0,
      "tech_torpedo_obtain": 0,
      "tech_torpedo_max": 0,
      "tech_torpedo_120": 0,
      "tech_aa_obtain": 0,
      "tech_aa_max": 0,
      "tech_aa_120": 0,
      "tech_aviation_obtain": 0,
      "tech_aviation_max": 0,
      "tech_aviation_120": 0,
      "tech_accuracy_obtain": 0,
      "tech_accuracy_max": 0,
      "tech_accuracy_120": 0,
      "tech_reload_obtain": 0,
      "tech_reload_max": 0,
      "tech_reload_120": 0,
      "tech_mobility_obtain": 0,
      "tech_mobility_max": 0,
      "tech_mobility_120": 0,
      "tech_antisub_obtain": 0,
      "tech_antisub_max": 0,
      "tech_antisub_120": 0,
      "image_path": "image/stephen_potter.png"
    },
    {
      "id": 515,
      "name": "莫里森",
      "faction": "白鹰",
      "ship_class": "驱逐",
      "rarity": "精锐",
      "owned": false,
      "breakthrough": 0,
      "can_remodel": false,
      "remodel_date": "",
      "remodeled": false,
      "oath": false,
      "level_120": false,
      "acquire_main": "商店兑换",
      "acquire_detail": "",
      "build_time": "",
      "drop_locations": [],
      "shop_exchange": "军需商店8000功勋值兑换、镜位螺旋活动累计PT奖励",
      "is_permanent": true,
      "debut_event": "镜位螺旋",
      "release_date": "2021-05-27",
      "notes": "",
      "tech_points_obtain": 8,
      "tech_points_max": 17,
      "tech_points_120": 13,
      "bonus_obtain": [],
      "bonus_120": [],
      "tech_affects": [
        "驱逐"
      ],
      "tech_durability_obtain": 1,
      "tech_durability_max": 0,
      "tech_durability_120": 0,
      "tech_firepower_obtain": 0,
      "tech_firepower_max": 0,
      "tech_firepower_120": 0,
      "tech_torpedo_obtain": 0,
      "tech_torpedo_max": 0,
      "tech_torpedo_120": 0,
      "tech_aa_obtain": 0,
      "tech_aa_max": 0,
      "tech_aa_120": 0,
      "tech_aviation_obtain": 0,
      "tech_aviation_max": 0,
      "tech_aviation_120": 0,
      "tech_accuracy_obtain": 0,
      "tech_accuracy_max": 0,
      "tech_accuracy_120": 0,
      "tech_reload_obtain": 0,
      "tech_reload_max": 0,
      "tech_reload_120": 0,
      "tech_mobility_obtain": 0,
      "tech_mobility_max": 0,
      "tech_mobility_120": 0,
      "tech_antisub_obtain": 0,
      "tech_antisub_max": 0,
      "tech_antisub_120": 1,
      "image_path": "image/morrison.png"
    },
    {
      "id": 417,
      "name": "斯莫利",
      "faction": "白鹰",
      "ship_class": "驱逐",
      "rarity": "稀有",
      "owned": false,
      "breakthrough": 0,
      "can_remodel": false,
      "remodel_date": "",
      "remodeled": false,
      "oath": false,
      "level_120": false,
      "acquire_main": "轻型池建造",
      "acquire_detail": "",
      "build_time": "00:28:00（轻型池）",
      "drop_locations": [],
      "shop_exchange": "",
      "is_permanent": true,
      "debut_event": "",
      "release_date": "2019-10-23",
      "notes": "",
      "tech_points_obtain": 6,
      "tech_points_max": 13,
      "tech_points_120": 9,
      "bonus_obtain": [],
      "bonus_120": [],
      "tech_affects": [
        "驱逐"
      ],
      "tech_durability_obtain": 1,
      "tech_durability_max": 0,
      "tech_durability_120": 0,
      "tech_firepower_obtain": 0,
      "tech_firepower_max": 0,
      "tech_firepower_120": 0,
      "tech_torpedo_obtain": 0,
      "tech_torpedo_max": 0,
      "tech_torpedo_120": 0,
      "tech_aa_obtain": 0,
      "tech_aa_max": 0,
      "tech_aa_120": 1,
      "tech_aviation_obtain": 0,
      "tech_aviation_max": 0,
      "tech_aviation_120": 0,
      "tech_accuracy_obtain": 0,
      "tech_accuracy_max": 0,
      "tech_accuracy_120": 0,
      "tech_reload_obtain": 0,
      "tech_reload_max": 0,
      "tech_reload_120": 0,
      "tech_mobility_obtain": 0,
      "tech_mobility_max": 0,
      "tech_mobility_120": 0,
      "tech_antisub_obtain": 0,
      "tech_antisub_max": 0,
      "tech_antisub_120": 0,
      "image_path": "image/smalley.png"
    },
    {
      "id": 15,
      "name": "奥利克",
      "faction": "白鹰",
      "ship_class": "驱逐",
      "rarity": "普通",
      "owned": false,
      "breakthrough": 0,
      "can_remodel": false,
      "remodel_date": "",
      "remodeled": false,
      "oath": false,
      "level_120": false,
      "acquire_main": "轻型池建造、打捞、勋章支援概率获得",
      "acquire_detail": "下方仅列出普通掉落点",
      "build_time": "00:28:00（轻型池）",
      "drop_locations": [
        "1-2、1-3、1-4、2-3、2-4、3-1、3-3、3-4、4-2、5-2、6-1、6-2、6-4、7-3、7-4、9-1、9-2、9-3、9-4、13-1、13-2、13-3、13-4、14-1、14-2、14-3、14-4、15-1、15-2、15-3、15-4"
      ],
      "shop_exchange": "",
      "is_permanent": true,
      "debut_event": "",
      "release_date": "2017-05-25",
      "notes": "",
      "tech_points_obtain": 4,
      "tech_points_max": 8,
      "tech_points_120": 6,
      "bonus_obtain": [],
      "bonus_120": [],
      "tech_affects": [
        "驱逐"
      ],
      "tech_durability_obtain": 1,
      "tech_durability_max": 0,
      "tech_durability_120": 1,
      "tech_firepower_obtain": 0,
      "tech_firepower_max": 0,
      "tech_firepower_120": 0,
      "tech_torpedo_obtain": 0,
      "tech_torpedo_max": 0,
      "tech_torpedo_120": 0,
      "tech_aa_obtain": 0,
      "tech_aa_max": 0,
      "tech_aa_120": 0,
      "tech_aviation_obtain": 0,
      "tech_aviation_max": 0,
      "tech_aviation_120": 0,
      "tech_accuracy_obtain": 0,
      "tech_accuracy_max": 0,
      "tech_accuracy_120": 0,
      "tech_reload_obtain": 0,
      "tech_reload_max": 0,
      "tech_reload_120": 0,
      "tech_mobility_obtain": 0,
      "tech_mobility_max": 0,
      "tech_mobility_120": 0,
      "tech_antisub_obtain": 0,
      "tech_antisub_max": 0,
      "tech_antisub_120": 0,
      "image_path": "image/aulick.png"
    },
    {
      "id": 13,
      "name": "查尔斯·奥斯本",
      "faction": "白鹰",
      "ship_class": "驱逐",
      "rarity": "精锐",
      "owned": false,
      "breakthrough": 0,
      "can_remodel": true,
      "remodel_date": "2022-08-18",
      "remodeled": false,
      "oath": false,
      "level_120": false,
      "acquire_main": "打捞、勋章支援概率获得",
      "acquire_detail": "下方仅列出普通掉落点",
      "build_time": "无法建造",
      "drop_locations": [
        "3-2、4-1、8-3、9-1"
      ],
      "shop_exchange": "",
      "is_permanent": true,
      "debut_event": "",
      "release_date": "2017-05-25",
      "notes": "",
      "tech_points_obtain": 8,
      "tech_points_max": 17,
      "tech_points_120": 13,
      "bonus_obtain": [],
      "bonus_120": [],
      "tech_affects": [
        "驱逐"
      ],
      "tech_durability_obtain": 1,
      "tech_durability_max": 0,
      "tech_durability_120": 0,
      "tech_firepower_obtain": 0,
      "tech_firepower_max": 0,
      "tech_firepower_120": 0,
      "tech_torpedo_obtain": 0,
      "tech_torpedo_max": 0,
      "tech_torpedo_120": 0,
      "tech_aa_obtain": 0,
      "tech_aa_max": 0,
      "tech_aa_120": 0,
      "tech_aviation_obtain": 0,
      "tech_aviation_max": 0,
      "tech_aviation_120": 0,
      "tech_accuracy_obtain": 0,
      "tech_accuracy_max": 0,
      "tech_accuracy_120": 0,
      "tech_reload_obtain": 0,
      "tech_reload_max": 0,
      "tech_reload_120": 0,
      "tech_mobility_obtain": 0,
      "tech_mobility_max": 0,
      "tech_mobility_120": 1,
      "tech_antisub_obtain": 0,
      "tech_antisub_max": 0,
      "tech_antisub_120": 0,
      "image_path": "image/charles_ausburne.png"
    },
    {
      "id": 12,
      "name": "威廉·D·波特",
      "faction": "白鹰",
      "ship_class": "驱逐",
      "rarity": "海上传奇",
      "owned": false,
      "breakthrough": 0,
      "can_remodel": false,
      "remodel_date": "",
      "remodeled": false,
      "oath": false,
      "level_120": false,
      "acquire_main": "商店兑换",
      "acquire_detail": "",
      "build_time": "无法建造",
      "drop_locations": [],
      "shop_exchange": "响彻于天穹之音PT商店兑换",
      "is_permanent": true,
      "debut_event": "响彻于天穹之音",
      "release_date": "2025-12-18",
      "notes": "",
      "tech_points_obtain": 15,
      "tech_points_max": 30,
      "tech_points_120": 23,
      "bonus_obtain": [],
      "bonus_120": [],
      "tech_affects": [
        "驱逐"
      ],
      "tech_durability_obtain": 0,
      "tech_durability_max": 0,
      "tech_durability_120": 2,
      "tech_firepower_obtain": 1,
      "tech_firepower_max": 0,
      "tech_firepower_120": 0,
      "tech_torpedo_obtain": 0,
      "tech_torpedo_max": 0,
      "tech_torpedo_120": 0,
      "tech_aa_obtain": 0,
      "tech_aa_max": 0,
      "tech_aa_120": 0,
      "tech_aviation_obtain": 0,
      "tech_aviation_max": 0,
      "tech_aviation_120": 0,
      "tech_accuracy_obtain": 0,
      "tech_accuracy_max": 0,
      "tech_accuracy_120": 0,
      "tech_reload_obtain": 0,
      "tech_reload_max": 0,
      "tech_reload_120": 0,
      "tech_mobility_obtain": 0,
      "tech_mobility_max": 0,
      "tech_mobility_120": 0,
      "tech_antisub_obtain": 0,
      "tech_antisub_max": 0,
      "tech_antisub_120": 0,
      "image_path": ""
    },
    {
      "id": 659,
      "name": "贝尔",
      "faction": "白鹰",
      "ship_class": "驱逐",
      "rarity": "精锐",
      "owned": false,
      "breakthrough": 0,
      "can_remodel": false,
      "remodel_date": "",
      "remodeled": false,
      "oath": false,
      "level_120": false,
      "acquire_main": "建造",
      "acquire_detail": "铁翼擎风期间限定建造",
      "build_time": "00:28:00（期间限定）",
      "drop_locations": [],
      "shop_exchange": "",
      "is_permanent": true,
      "debut_event": "铁翼擎风",
      "release_date": "2024-08-15",
      "notes": "",
      "tech_points_obtain": 8,
      "tech_points_max": 17,
      "tech_points_120": 13,
      "bonus_obtain": [],
      "bonus_120": [],
      "tech_affects": [
        "驱逐"
      ],
      "tech_durability_obtain": 1,
      "tech_durability_max": 0,
      "tech_durability_120": 0,
      "tech_firepower_obtain": 0,
      "tech_firepower_max": 0,
      "tech_firepower_120": 0,
      "tech_torpedo_obtain": 0,
      "tech_torpedo_max": 0,
      "tech_torpedo_120": 0,
      "tech_aa_obtain": 0,
      "tech_aa_max": 0,
      "tech_aa_120": 0,
      "tech_aviation_obtain": 0,
      "tech_aviation_max": 0,
      "tech_aviation_120": 0,
      "tech_accuracy_obtain": 0,
      "tech_accuracy_max": 0,
      "tech_accuracy_120": 0,
      "tech_reload_obtain": 0,
      "tech_reload_max": 0,
      "tech_reload_120": 0,
      "tech_mobility_obtain": 0,
      "tech_mobility_max": 0,
      "tech_mobility_120": 0,
      "tech_antisub_obtain": 0,
      "tech_antisub_max": 0,
      "tech_antisub_120": 1,
      "image_path": "image/bell.png"
    },
    {
      "id": 718,
      "name": "克拉伦斯·K·布朗森",
      "faction": "白鹰",
      "ship_class": "驱逐",
      "rarity": "精锐",
      "owned": false,
      "breakthrough": 0,
      "can_remodel": false,
      "remodel_date": "",
      "remodeled": false,
      "oath": false,
      "level_120": false,
      "acquire_main": "活动赠送",
      "acquire_detail": "响彻于天穹之音活动理事会PT累计奖励",
      "build_time": "无法建造",
      "drop_locations": [],
      "shop_exchange": "",
      "is_permanent": true,
      "debut_event": "响彻于天穹之音",
      "release_date": "2025-12-18",
      "notes": "",
      "tech_points_obtain": 8,
      "tech_points_max": 17,
      "tech_points_120": 13,
      "bonus_obtain": [],
      "bonus_120": [],
      "tech_affects": [
        "驱逐"
      ],
      "tech_durability_obtain": 1,
      "tech_durability_max": 0,
      "tech_durability_120": 0,
      "tech_firepower_obtain": 0,
      "tech_firepower_max": 0,
      "tech_firepower_120": 0,
      "tech_torpedo_obtain": 0,
      "tech_torpedo_max": 0,
      "tech_torpedo_120": 0,
      "tech_aa_obtain": 0,
      "tech_aa_max": 0,
      "tech_aa_120": 0,
      "tech_aviation_obtain": 0,
      "tech_aviation_max": 0,
      "tech_aviation_120": 0,
      "tech_accuracy_obtain": 0,
      "tech_accuracy_max": 0,
      "tech_accuracy_120": 0,
      "tech_reload_obtain": 0,
      "tech_reload_max": 0,
      "tech_reload_120": 0,
      "tech_mobility_obtain": 0,
      "tech_mobility_max": 0,
      "tech_mobility_120": 0,
      "tech_antisub_obtain": 0,
      "tech_antisub_max": 0,
      "tech_antisub_120": 1,
      "image_path": "image/clarence_k_bronson.png"
    },
    {
      "id": 427,
      "name": "哈尔西·鲍威尔",
      "faction": "白鹰",
      "ship_class": "驱逐",
      "rarity": "稀有",
      "owned": false,
      "breakthrough": 0,
      "can_remodel": false,
      "remodel_date": "",
      "remodeled": false,
      "oath": false,
      "level_120": false,
      "acquire_main": "打捞、商店兑换、勋章支援概率获得",
      "acquire_detail": "",
      "build_time": "无法建造",
      "drop_locations": [
        "15-1"
      ],
      "shop_exchange": "舰队商店300舰队币兑换",
      "is_permanent": true,
      "debut_event": "战斗！皇家女仆队2nd",
      "release_date": "2020-01-21",
      "notes": "",
      "tech_points_obtain": 6,
      "tech_points_max": 13,
      "tech_points_120": 9,
      "bonus_obtain": [],
      "bonus_120": [],
      "tech_affects": [
        "驱逐"
      ],
      "tech_durability_obtain": 1,
      "tech_durability_max": 0,
      "tech_durability_120": 0,
      "tech_firepower_obtain": 0,
      "tech_firepower_max": 0,
      "tech_firepower_120": 0,
      "tech_torpedo_obtain": 0,
      "tech_torpedo_max": 0,
      "tech_torpedo_120": 0,
      "tech_aa_obtain": 0,
      "tech_aa_max": 0,
      "tech_aa_120": 1,
      "tech_aviation_obtain": 0,
      "tech_aviation_max": 0,
      "tech_aviation_120": 0,
      "tech_accuracy_obtain": 0,
      "tech_accuracy_max": 0,
      "tech_accuracy_120": 0,
      "tech_reload_obtain": 0,
      "tech_reload_max": 0,
      "tech_reload_120": 0,
      "tech_mobility_obtain": 0,
      "tech_mobility_max": 0,
      "tech_mobility_120": 0,
      "tech_antisub_obtain": 0,
      "tech_antisub_max": 0,
      "tech_antisub_120": 0,
      "image_path": "image/halsey_powell.png"
    },
    {
      "id": 508,
      "name": "艾伦·萨姆纳",
      "faction": "白鹰",
      "ship_class": "驱逐",
      "rarity": "超稀有",
      "owned": false,
      "breakthrough": 0,
      "can_remodel": false,
      "remodel_date": "",
      "remodeled": false,
      "oath": false,
      "level_120": false,
      "acquire_main": "商店兑换、勋章支援概率获得",
      "acquire_detail": "",
      "build_time": "无法建造",
      "drop_locations": [],
      "shop_exchange": "勋章商店80荣誉勋章兑换",
      "is_permanent": true,
      "debut_event": "复刻:箱庭疗法",
      "release_date": "2021-03-25",
      "notes": "",
      "tech_points_obtain": 12,
      "tech_points_max": 24,
      "tech_points_120": 18,
      "bonus_obtain": [],
      "bonus_120": [],
      "tech_affects": [
        "驱逐"
      ],
      "tech_durability_obtain": 0,
      "tech_durability_max": 0,
      "tech_durability_120": 2,
      "tech_firepower_obtain": 1,
      "tech_firepower_max": 0,
      "tech_firepower_120": 0,
      "tech_torpedo_obtain": 0,
      "tech_torpedo_max": 0,
      "tech_torpedo_120": 0,
      "tech_aa_obtain": 0,
      "tech_aa_max": 0,
      "tech_aa_120": 0,
      "tech_aviation_obtain": 0,
      "tech_aviation_max": 0,
      "tech_aviation_120": 0,
      "tech_accuracy_obtain": 0,
      "tech_accuracy_max": 0,
      "tech_accuracy_120": 0,
      "tech_reload_obtain": 0,
      "tech_reload_max": 0,
      "tech_reload_120": 0,
      "tech_mobility_obtain": 0,
      "tech_mobility_max": 0,
      "tech_mobility_120": 0,
      "tech_antisub_obtain": 0,
      "tech_antisub_max": 0,
      "tech_antisub_120": 0,
      "image_path": "image/allen_m_summer/png"
    },
    {
      "id": 518,
      "name": "英格拉罕",
      "faction": "白鹰",
      "ship_class": "驱逐",
      "rarity": "超稀有",
      "owned": false,
      "breakthrough": 0,
      "can_remodel": false,
      "remodel_date": "",
      "remodeled": false,
      "oath": false,
      "level_120": false,
      "acquire_main": "轻型池建造",
      "acquire_detail": "",
      "build_time": "00:29:00（轻型池）",
      "drop_locations": [],
      "shop_exchange": "",
      "is_permanent": true,
      "debut_event": "复刻:微层混合",
      "release_date": "2021-08-19",
      "notes": "",
      "tech_points_obtain": 12,
      "tech_points_max": 24,
      "tech_points_120": 18,
      "bonus_obtain": [],
      "bonus_120": [],
      "tech_affects": [
        "驱逐"
      ],
      "tech_durability_obtain": 0,
      "tech_durability_max": 0,
      "tech_durability_120": 2,
      "tech_firepower_obtain": 0,
      "tech_firepower_max": 0,
      "tech_firepower_120": 0,
      "tech_torpedo_obtain": 0,
      "tech_torpedo_max": 0,
      "tech_torpedo_120": 0,
      "tech_aa_obtain": 1,
      "tech_aa_max": 0,
      "tech_aa_120": 0,
      "tech_aviation_obtain": 0,
      "tech_aviation_max": 0,
      "tech_aviation_120": 0,
      "tech_accuracy_obtain": 0,
      "tech_accuracy_max": 0,
      "tech_accuracy_120": 0,
      "tech_reload_obtain": 0,
      "tech_reload_max": 0,
      "tech_reload_120": 0,
      "tech_mobility_obtain": 0,
      "tech_mobility_max": 0,
      "tech_mobility_120": 0,
      "tech_antisub_obtain": 0,
      "tech_antisub_max": 0,
      "tech_antisub_120": 0,
      "image_path": "image/ingraham.png"
    },
    {
      "id": 444,
      "name": "库珀",
      "faction": "白鹰",
      "ship_class": "驱逐",
      "rarity": "精锐",
      "owned": false,
      "breakthrough": 0,
      "can_remodel": false,
      "remodel_date": "",
      "remodeled": false,
      "oath": false,
      "level_120": false,
      "acquire_main": "轻型池建造",
      "acquire_detail": "",
      "build_time": "00:29:00（轻型池）",
      "drop_locations": [],
      "shop_exchange": "",
      "is_permanent": true,
      "debut_event": "微层混合",
      "release_date": "2020-03-26",
      "notes": "",
      "tech_points_obtain": 9,
      "tech_points_max": 19,
      "tech_points_120": 14,
      "bonus_obtain": [],
      "bonus_120": [],
      "tech_affects": [
        "驱逐"
      ],
      "tech_durability_obtain": 1,
      "tech_durability_max": 0,
      "tech_durability_120": 0,
      "tech_firepower_obtain": 0,
      "tech_firepower_max": 0,
      "tech_firepower_120": 1,
      "tech_torpedo_obtain": 0,
      "tech_torpedo_max": 0,
      "tech_torpedo_120": 0,
      "tech_aa_obtain": 0,
      "tech_aa_max": 0,
      "tech_aa_120": 0,
      "tech_aviation_obtain": 0,
      "tech_aviation_max": 0,
      "tech_aviation_120": 0,
      "tech_accuracy_obtain": 0,
      "tech_accuracy_max": 0,
      "tech_accuracy_120": 0,
      "tech_reload_obtain": 0,
      "tech_reload_max": 0,
      "tech_reload_120": 0,
      "tech_mobility_obtain": 0,
      "tech_mobility_max": 0,
      "tech_mobility_120": 0,
      "tech_antisub_obtain": 0,
      "tech_antisub_max": 0,
      "tech_antisub_120": 0,
      "image_path": "image/cooper.png"
    },
    {
      "id": 615,
      "name": "拉菲II",
      "faction": "白鹰",
      "ship_class": "驱逐",
      "rarity": "海上传奇",
      "owned": false,
      "breakthrough": 0,
      "can_remodel": false,
      "remodel_date": "",
      "remodeled": false,
      "oath": false,
      "level_120": false,
      "acquire_main": "商店兑换",
      "acquire_detail": "",
      "build_time": "无法建造",
      "drop_locations": [],
      "shop_exchange": "星海逐光活动「破损信标」兑换",
      "is_permanent": true,
      "debut_event": "星海逐光",
      "release_date": "2023-12-21",
      "notes": "",
      "tech_points_obtain": 16,
      "tech_points_max": 33,
      "tech_points_120": 25,
      "bonus_obtain": [],
      "bonus_120": [],
      "tech_affects": [
        "驱逐"
      ],
      "tech_durability_obtain": 0,
      "tech_durability_max": 0,
      "tech_durability_120": 2,
      "tech_firepower_obtain": 1,
      "tech_firepower_max": 0,
      "tech_firepower_120": 0,
      "tech_torpedo_obtain": 0,
      "tech_torpedo_max": 0,
      "tech_torpedo_120": 0,
      "tech_aa_obtain": 0,
      "tech_aa_max": 0,
      "tech_aa_120": 0,
      "tech_aviation_obtain": 0,
      "tech_aviation_max": 0,
      "tech_aviation_120": 0,
      "tech_accuracy_obtain": 0,
      "tech_accuracy_max": 0,
      "tech_accuracy_120": 0,
      "tech_reload_obtain": 0,
      "tech_reload_max": 0,
      "tech_reload_120": 0,
      "tech_mobility_obtain": 0,
      "tech_mobility_max": 0,
      "tech_mobility_120": 0,
      "tech_antisub_obtain": 0,
      "tech_antisub_max": 0,
      "tech_antisub_120": 0,
      "image_path": "image/laffey_ii.png"
    },
    {
      "id": 533,
      "name": "布里斯托尔",
      "faction": "白鹰",
      "ship_class": "驱逐",
      "rarity": "超稀有",
      "owned": false,
      "breakthrough": 0,
      "can_remodel": false,
      "remodel_date": "",
      "remodeled": false,
      "oath": false,
      "level_120": false,
      "acquire_main": "轻型池建造、贺年卡兑换",
      "acquire_detail": "「贺年卡（甲辰）」可选",
      "build_time": "00:29:00（轻型池）",
      "drop_locations": [],
      "shop_exchange": "",
      "is_permanent": true,
      "debut_event": "演习神秘事件调查",
      "release_date": "2022-01-27",
      "notes": "",
      "tech_points_obtain": 12,
      "tech_points_max": 24,
      "tech_points_120": 18,
      "bonus_obtain": [],
      "bonus_120": [],
      "tech_affects": [
        "驱逐"
      ],
      "tech_durability_obtain": 0,
      "tech_durability_max": 0,
      "tech_durability_120": 2,
      "tech_firepower_obtain": 1,
      "tech_firepower_max": 0,
      "tech_firepower_120": 0,
      "tech_torpedo_obtain": 0,
      "tech_torpedo_max": 0,
      "tech_torpedo_120": 0,
      "tech_aa_obtain": 0,
      "tech_aa_max": 0,
      "tech_aa_120": 0,
      "tech_aviation_obtain": 0,
      "tech_aviation_max": 0,
      "tech_aviation_120": 0,
      "tech_accuracy_obtain": 0,
      "tech_accuracy_max": 0,
      "tech_accuracy_120": 0,
      "tech_reload_obtain": 0,
      "tech_reload_max": 0,
      "tech_reload_120": 0,
      "tech_mobility_obtain": 0,
      "tech_mobility_max": 0,
      "tech_mobility_120": 0,
      "tech_antisub_obtain": 0,
      "tech_antisub_max": 0,
      "tech_antisub_120": 0,
      "image_path": "image/brisol.png"
    },
    {
      "id": 28,
      "name": "埃尔德里奇",
      "faction": "白鹰",
      "ship_class": "驱逐",
      "rarity": "超稀有",
      "owned": false,
      "breakthrough": 0,
      "can_remodel": true,
      "remodel_date": "2024-08-15",
      "remodeled": false,
      "oath": false,
      "level_120": false,
      "acquire_main": "商店兑换",
      "acquire_detail": "",
      "build_time": "无法建造",
      "drop_locations": [],
      "shop_exchange": "军需商店20000功勋值兑换",
      "is_permanent": true,
      "debut_event": "",
      "release_date": "2017-05-25",
      "notes": "",
      "tech_points_obtain": 7,
      "tech_points_max": 14,
      "tech_points_120": 10,
      "bonus_obtain": [],
      "bonus_120": [],
      "tech_affects": [
        "驱逐"
      ],
      "tech_durability_obtain": 0,
      "tech_durability_max": 0,
      "tech_durability_120": 0,
      "tech_firepower_obtain": 0,
      "tech_firepower_max": 0,
      "tech_firepower_120": 0,
      "tech_torpedo_obtain": 0,
      "tech_torpedo_max": 0,
      "tech_torpedo_120": 0,
      "tech_aa_obtain": 0,
      "tech_aa_max": 0,
      "tech_aa_120": 1,
      "tech_aviation_obtain": 0,
      "tech_aviation_max": 0,
      "tech_aviation_120": 0,
      "tech_accuracy_obtain": 0,
      "tech_accuracy_max": 0,
      "tech_accuracy_120": 0,
      "tech_reload_obtain": 0,
      "tech_reload_max": 0,
      "tech_reload_120": 0,
      "tech_mobility_obtain": 0,
      "tech_mobility_max": 0,
      "tech_mobility_120": 0,
      "tech_antisub_obtain": 1,
      "tech_antisub_max": 0,
      "tech_antisub_120": 0,
      "image_path": "image/eldridge.png"
    },
    {
      "id": 576,
      "name": "哈曼II",
      "faction": "白鹰",
      "ship_class": "驱逐",
      "rarity": "精锐",
      "owned": false,
      "breakthrough": 0,
      "can_remodel": false,
      "remodel_date": "",
      "remodeled": false,
      "oath": false,
      "level_120": false,
      "acquire_main": "轻型池建造",
      "acquire_detail": "",
      "build_time": "00:15:00（轻型池）",
      "drop_locations": [],
      "shop_exchange": "",
      "is_permanent": true,
      "debut_event": "定向折叠",
      "release_date": "2022-12-22",
      "notes": "",
      "tech_points_obtain": 5,
      "tech_points_max": 11,
      "tech_points_120": 8,
      "bonus_obtain": [],
      "bonus_120": [],
      "tech_affects": [
        "驱逐"
      ],
      "tech_durability_obtain": 0,
      "tech_durability_max": 0,
      "tech_durability_120": 0,
      "tech_firepower_obtain": 0,
      "tech_firepower_max": 0,
      "tech_firepower_120": 0,
      "tech_torpedo_obtain": 0,
      "tech_torpedo_max": 0,
      "tech_torpedo_120": 0,
      "tech_aa_obtain": 0,
      "tech_aa_max": 0,
      "tech_aa_120": 1,
      "tech_aviation_obtain": 0,
      "tech_aviation_max": 0,
      "tech_aviation_120": 0,
      "tech_accuracy_obtain": 0,
      "tech_accuracy_max": 0,
      "tech_accuracy_120": 0,
      "tech_reload_obtain": 0,
      "tech_reload_max": 0,
      "tech_reload_120": 0,
      "tech_mobility_obtain": 0,
      "tech_mobility_max": 0,
      "tech_mobility_120": 0,
      "tech_antisub_obtain": 1,
      "tech_antisub_max": 0,
      "tech_antisub_120": 0,
      "image_path": "image/hammann_ii.png"
    },
    {
      "id": 29,
      "name": "奥马哈",
      "faction": "白鹰",
      "ship_class": "轻巡",
      "rarity": "普通",
      "owned": false,
      "breakthrough": 0,
      "can_remodel": false,
      "remodel_date": "",
      "remodeled": false,
      "oath": false,
      "level_120": false,
      "acquire_main": "轻型池建造、打捞、勋章支援概率获得",
      "acquire_detail": "下方仅列出普通掉落点",
      "build_time": "01:05:00（轻型池）",
      "drop_locations": [
        "1-4、2-1、2-2、2-3、2-4、3-1、3-2、3-3、4-1、4-3、5-1、6-4、7-4、9-1、9-2、9-3、9-4、10-1、10-2、10-3、10-4、11-1、11-2、11-3、11-4、15-1、15-2、15-3、15-4、16-1、16-2、16-3、16-4"
      ],
      "shop_exchange": "",
      "is_permanent": true,
      "debut_event": "",
      "release_date": "2017-05-25",
      "notes": "",
      "tech_points_obtain": 3,
      "tech_points_max": 7,
      "tech_points_120": 5,
      "bonus_obtain": [],
      "bonus_120": [],
      "tech_affects": [
        "轻巡"
      ],
      "tech_durability_obtain": 1,
      "tech_durability_max": 0,
      "tech_durability_120": 1,
      "tech_firepower_obtain": 0,
      "tech_firepower_max": 0,
      "tech_firepower_120": 0,
      "tech_torpedo_obtain": 0,
      "tech_torpedo_max": 0,
      "tech_torpedo_120": 0,
      "tech_aa_obtain": 0,
      "tech_aa_max": 0,
      "tech_aa_120": 0,
      "tech_aviation_obtain": 0,
      "tech_aviation_max": 0,
      "tech_aviation_120": 0,
      "tech_accuracy_obtain": 0,
      "tech_accuracy_max": 0,
      "tech_accuracy_120": 0,
      "tech_reload_obtain": 0,
      "tech_reload_max": 0,
      "tech_reload_120": 0,
      "tech_mobility_obtain": 0,
      "tech_mobility_max": 0,
      "tech_mobility_120": 0,
      "tech_antisub_obtain": 0,
      "tech_antisub_max": 0,
      "tech_antisub_120": 0,
      "image_path": "image/omaha.png"
    }
  ]
}